adbcug_adapter/__init__.py
adbcug_adapter/abc.py
adbcug_adapter/adapter.py
adbcug_adapter/controller.py
adbcug_adapter/typings.py
adbcug_adapter/utils.py
adbcug_adapter-2.0.2.dist-info/LICENSE
adbcug_adapter-2.0.2.dist-info/METADATA
adbcug_adapter-2.0.2.dist-info/WHEEL
adbcug_adapter-2.0.2.dist-info/top_level.txt
adbcug_adapter-2.0.2.dist-info/RECORD
