Metadata-Version: 2.1
Name: adbcug_adapter
Version: 2.0.2
Summary: Convert ArangoDB graphs to cuGraph & vice-versa.
Author-email: Anthony Mahanna <anthony.mahanna@arangodb.com>
License: Apache License
Project-URL: Homepage, https://github.com/arangoml/cugraph-adapter
Keywords: arangodb,cugraph,adapter
Classifier: Intended Audience :: Developers
Classifier: License :: OSI Approved :: Apache Software License
Classifier: Operating System :: OS Independent
Classifier: Programming Language :: Python :: 3
Classifier: Programming Language :: Python :: 3.9
Classifier: Programming Language :: Python :: 3.10
Classifier: Topic :: Utilities
Classifier: Typing :: Typed
Requires-Python: <3.11,>=3.9
License-File: LICENSE
Requires-Dist: python-arango ~=7.6
Requires-Dist: rich >=12.5.1
Requires-Dist: setuptools >=42
Provides-Extra: dev
Requires-Dist: black ==23.3.0 ; extra == 'dev'
Requires-Dist: flake8 ==6.0.0 ; extra == 'dev'
Requires-Dist: Flake8-pyproject ; extra == 'dev'
Requires-Dist: isort ==5.12.0 ; extra == 'dev'
Requires-Dist: mypy ==1.4.1 ; extra == 'dev'
Requires-Dist: pytest >=6.0.0 ; extra == 'dev'
Requires-Dist: pytest-cov >=2.0.0 ; extra == 'dev'
Requires-Dist: coveralls >=3.3.1 ; extra == 'dev'
Requires-Dist: types-setuptools ; extra == 'dev'
